geesarfetcher/__init__.py
geesarfetcher/api.py
geesarfetcher/assertions.py
geesarfetcher/constants.py
geesarfetcher/coordinates.py
geesarfetcher/exceptions.py
geesarfetcher/fetcher.py
geesarfetcher/filter.py
geesarfetcher/utils/__init__.py
tests/__init__.py
tests/test_fetcher.py
geesarfetcher-0.3.8.dist-info/LICENSE
geesarfetcher-0.3.8.dist-info/METADATA
geesarfetcher-0.3.8.dist-info/WHEEL
geesarfetcher-0.3.8.dist-info/top_level.txt
geesarfetcher-0.3.8.dist-info/RECORD
