Metadata-Version: 2.1
Name: geesarfetcher
Version: 0.3.8
Summary: Extract Sentinel-1 GRD time-series images over a given area from google earth engine
Home-page: https://github.com/dimartinot/gee_sar_fetcher
Author: Thomas Di Martino
Author-email: thomas.di-martino@hotmail.com
License: MIT
Keywords: SAR,sentinel,google,gee,time-series,radar,satellite imagery
Platform: UNKNOWN
License-File: LICENSE
Requires-Dist: tqdm (>=4.50.2)
Requires-Dist: numpy (<=1.19.3,>=1.18.0)
Requires-Dist: earthengine-api (>=0.1.231)
Requires-Dist: joblib (>=0.17.0)
Requires-Dist: google-auth (<2.0dev,>=1.11.0)
Provides-Extra: all
Requires-Dist: sphinx ; extra == 'all'
Requires-Dist: sphinxcontrib-programoutput ; extra == 'all'
Requires-Dist: sphinx-rtd-theme ; extra == 'all'
Provides-Extra: docs
Requires-Dist: sphinx ; extra == 'docs'
Requires-Dist: sphinx-rtd-theme ; extra == 'docs'
Requires-Dist: sphinxcontrib-programoutput ; extra == 'docs'
